practise/fifo/asyn_fifo/ram.v
module ram #(
    parameter DATA_BIT_WIDTH   = 8,
    parameter DATA_DEPTH       = 16,
    parameter DATA_DEPTH_WIDTH = 4
) (
    input r_clk,
    input w_clk,
    // input rst, // 建议移除：RAM 通常不需要复位

    // 写端口
    input                        wen,
    input [DATA_DEPTH_WIDTH-1:0] waddr,  // 修正：范围必须是 [N-1 : 0]
    input [  DATA_BIT_WIDTH-1:0] wdata,

    // 读端口
    input                             ren,
    input      [DATA_DEPTH_WIDTH-1:0] raddr,
    output reg [  DATA_BIT_WIDTH-1:0] rdata   // 修正：添加 reg 且修复位宽
);

  // 声明内存数组
  // 格式：reg [位宽] 名字 [深度]
  reg [DATA_BIT_WIDTH-1:0] mem[0:DATA_DEPTH-1];

  // --- 写逻辑 ---
  always @(posedge w_clk) begin
    if (wen) begin
      mem[waddr] <= wdata;
    end
  end

  // --- 读逻辑 ---
  always @(posedge r_clk) begin
    if (ren) begin
      rdata <= mem[raddr];
    end
    // 如果你需要 rst 复位输出端口的数据（而不是复位整个RAM数组），可以写在这里：
    // else if (rst) rdata <= 0;
    // 但通常为了性能，BRAM 的输出端也不加复位。
  end

endmodule

practise/fifo/asyn_fifo/fifo.v
module fifo #(
    parameter DATA_BIT_WIDTH = 8,
    parameter DATA_DEPTH     = 16
) (
    input rst,

    // Write Interface
    input                      w_clk,
    input                      wen,
    input [DATA_BIT_WIDTH-1:0] wdata,

    // Read Interface
    input                       r_clk,
    input                       ren,
    output [DATA_BIT_WIDTH-1:0] rdata,

    // Status Interface
    output full,
    output empty
    // --- 修复点：直接在这里计算位宽 ---
    // 深度为16时，log2(16)=4。计数器需要能存下16(10000)，即5位([4:0])。
);

  // 内部参数定义
  localparam ADDR_WIDTH = $clog2(DATA_DEPTH);  // 例如 4
  localparam PTR_WIDTH = ADDR_WIDTH + 1;  // 例如 5

  reg [PTR_WIDTH-1 : 0] w_bin, r_bin;  // read and write ptr
  wire [PTR_WIDTH-1 : 0] w_bin_next, r_bin_next;
  reg [PTR_WIDTH-1 : 0] w_gray, r_gray;
  wire [PTR_WIDTH-1 : 0] w_gray_next, r_gray_next;
  reg [PTR_WIDTH-1 : 0] w2r_meta, r2w_meta;  // meta 表示亚稳态
  reg [PTR_WIDTH-1 : 0] w2r_safe, r2w_safe;  // safe 表嫂稳定态

  assign w_bin_next  = w_bin + (wen && !full);
  assign r_bin_next  = r_bin + (ren && !empty);
  assign w_gray_next = (w_bin_next >> 1) ^ w_bin_next;
  assign r_gray_next = (r_bin_next >> 1) ^ r_bin_next;
  // 写指针
  always @(posedge w_clk) begin
    if (rst) begin
      w_bin  <= 0;
      w_gray <= 0;
    end else begin
      w_bin  <= w_bin_next;
      w_gray <= w_gray_next;
    end
  end

  // 读指针
  always @(posedge r_clk) begin
    if (rst) begin
      r_bin  <= 0;
      r_gray <= 0;
    end else begin
      r_bin  <= r_bin_next;
      r_gray <= r_gray_next;
    end
  end

  //不同时域的指针相互转化
  always @(posedge r_clk) begin
    if (rst) begin
      w2r_safe <= 0;
      w2r_meta <= 0;
    end else begin
      w2r_meta <= w_gray;
      w2r_safe <= w2r_meta;
    end
  end

  always @(posedge w_clk) begin
    if (rst) begin
      r2w_safe <= 0;
      r2w_meta <= 0;
    end else begin
      r2w_meta <= r_gray;
      r2w_safe <= r2w_meta;
    end
  end

  //空信号和满信号的产生
  assign full = (w_gray[PTR_WIDTH-1] != r2w_safe[PTR_WIDTH-1]) &&
                  (w_gray[PTR_WIDTH-2] != r2w_safe[PTR_WIDTH-2]) &&
                  (w_gray[ADDR_WIDTH-2:0] == r2w_safe[ADDR_WIDTH-2:0]);
  assign empty = (w2r_safe == r_gray);  //空信号一定在读时钟域产生

  // --- RAM 实例化 ---
  // 确保你的 ram.v 也是修正后的版本
  ram #(
      .DATA_BIT_WIDTH  (DATA_BIT_WIDTH),
      .DATA_DEPTH      (DATA_DEPTH),
      .DATA_DEPTH_WIDTH(ADDR_WIDTH)
  ) ram_inst (
      .r_clk(r_clk),
      .w_clk(w_clk),
      // .rst (rst), // 如果你的 RAM 不需要复位，这行可以注释掉；如果加了复位逻辑则保留

      .wen  (wen && !full),
      .waddr(w_bin[ADDR_WIDTH-1:0]),
      .wdata(wdata),

      .ren  (ren && !empty),
      .raddr(r_bin[ADDR_WIDTH-1:0]),
      .rdata(rdata)
  );

endmodule

practise/fifo/asyn_fifo/testbench.v
`timescale 1ns / 1ns

module tb_fifo;

  // --- 1. 参数定义 ---
  parameter DATA_BIT_WIDTH = 8;
  parameter DATA_DEPTH = 16;

  // --- 2. 信号声明 ---
  reg rst;

  // 写端口信号
  reg w_clk;
  reg wen;
  reg [DATA_BIT_WIDTH-1:0] wdata;

  // 读端口信号
  reg r_clk;
  reg ren;
  wire [DATA_BIT_WIDTH-1:0] rdata;

  // 状态信号
  wire full;
  wire empty;

  // 验证用变量
  integer i;
  reg [DATA_BIT_WIDTH-1:0] expected_data;

  // --- 3. 实例化待测模块 (DUT) ---
  fifo #(
      .DATA_BIT_WIDTH(DATA_BIT_WIDTH),
      .DATA_DEPTH    (DATA_DEPTH)
  ) u_fifo (
      .rst(rst),

      .w_clk(w_clk),
      .wen  (wen),
      .wdata(wdata),

      .r_clk(r_clk),
      .ren  (ren),
      .rdata(rdata),

      .full (full),
      .empty(empty)
  );

  // --- 4. 时钟生成 (模拟异步环境) ---
  // 写时钟：10ns 周期 (100 MHz)
  initial w_clk = 0;
  always #5 w_clk = ~w_clk;

  // 读时钟：16ns 周期 (62.5 MHz)
  initial r_clk = 0;
  always #8 r_clk = ~r_clk;

  // --- 5. 辅助任务：精确控制时序 ---
  // 关键策略：在下降沿操作信号，确保上升沿采样稳定
  task wait_w_clk_neg;
    @(negedge w_clk);
  endtask

  task wait_r_clk_neg;
    @(negedge r_clk);
  endtask

  // 等待上升沿（用于观察）
  task wait_r_clk_pos;
    @(posedge r_clk);
  endtask

  // --- 6. 测试主流程 ---
  initial begin
    // 波形输出配置
    // 兼容 Makefile 中的 +define+fsdb
`ifdef fsdb
    $fsdbDumpfile(
        "/home/jay/Desktop/graduation_project/practise/fifo/asyn_fifo/testbench.fsdb");  // 明确指定后缀，防止自动添加
    $fsdbDumpvars("+all");
`endif

    // 兼容通用的 VCD 输出
    $dumpfile("fifo_wave.vcd");
    $dumpvars(0, tb_fifo);

    // 初始化
    rst   = 1;
    wen   = 0;
    ren   = 0;
    wdata = 0;

    // 复位序列
    #50;
    rst = 0;  // 释放复位
    #50;

    $display("=== Simulation Start ===");

    // ================================================
    // [TEST 1] 写入数据直到满 (Write until Full)
    // ================================================
    $display("[TEST 1] Writing data 0 to 15...");

    for (i = 0; i < DATA_DEPTH; i = i + 1) begin
      // 1. 等待下降沿，准备驱动
      wait_w_clk_neg();

      // 2. 检查满信号 (Full信号是在写时钟域更新的，所以可以直接用)
      if (!full) begin
        wen   = 1;
        wdata = i;  // 写入 0, 1, 2...

        // 3. 【关键修复】保持信号直到下一个下降沿
        // 这样 wen 会像一个方框一样包住 posedge，绝对会被采到
        wait_w_clk_neg();

        wen   = 0;
        wdata = 0;
      end else begin
        $display("Warning: FIFO Full at %0d, skipping write", i);
        // 如果满了，也要消耗时间等待，避免死循环太快
        wait_w_clk_neg();
      end
    end

    // 等待一段时间，让写指针同步到读时钟域 (Empty 变 0)
    #200;

    // 简单的状态检查
    if (full) $display("SUCCESS: FIFO is Full properly.");
    else $display("ERROR: FIFO should be Full.");

    // ================================================
    // [TEST 2] 读取数据直到空 (Read until Empty)
    // ================================================
    $display("[TEST 2] Reading back data...");

    for (i = 0; i < DATA_DEPTH; i = i + 1) begin
      // 1. 异步等待 FIFO 非空
      // 注意：empty 变低可能有延迟
      while (empty) begin
        wait_r_clk_neg();
      end

      // 2. 发起读操作 (在下降沿拉高)
      wait_r_clk_neg();
      ren = 1;

      // 3. 【关键修复】保持有效直到下一个下降沿
      wait_r_clk_neg();
      ren = 0;

      // 4. 等待数据输出
      // RAM 行为：posedge r_clk 采样 ren -> 数据在 Tco 后输出
      // 因为我们刚刚经过了一个 negedge，离数据出来还有半个周期 + Tco
      // 为了稳妥，我们等待下一个上升沿来观察数据
      wait_r_clk_pos();
      #1;  // 微小延迟，模拟真实采样

      // 5. 数据比对
      expected_data = i;
      if (rdata === expected_data) begin
        $display("Read OK: Addr=%0d, Data=%0d (Time: %0t)", i, rdata, $time);
      end else begin
        $display("Read ERROR: Expected %0d, Got %0d (Time: %0t)", expected_data, rdata, $time);
      end
    end

    // 等待状态更新
    #200;

    if (empty) $display("SUCCESS: FIFO is Empty properly.");
    else $display("ERROR: FIFO should be Empty.");

    $display("=== Simulation End ===");
    $finish;
  end

endmodule

practise/fifo/asyn_fifo/fifo_wave.vcd
$date
	Sun Jan 18 10:51:20 2026
$end

$version
	Synopsys VCS version O-2018.09-SP2_Full64
$end

$timescale
	1ns
$end

$comment Csum: 1 85c04f127453a07f $end


$scope module tb_fifo $end
$var reg 1 ! rst $end
$var reg 1 " w_clk $end
$var reg 1 # wen $end
$var reg 8 $ wdata [7:0] $end
$var reg 1 % r_clk $end
$var reg 1 & ren $end
$var wire 8 ' rdata [7:0] $end
$var wire 1 ( full $end
$var wire 1 ) empty $end
$var integer 32 * i $end
$var reg 8 + expected_data [7:0] $end

$scope task wait_w_clk_neg $end
$upscope $end


$scope task wait_r_clk_neg $end
$upscope $end


$scope task wait_r_clk_pos $end
$upscope $end


$scope module u_fifo $end
$var wire 1 ! rst $end
$var wire 1 " w_clk $end
$var wire 1 # wen $end
$var wire 8 $ wdata [7:0] $end
$var wire 1 % r_clk $end
$var wire 1 & ren $end
$var wire 8 ' rdata [7:0] $end
$var wire 1 ( full $end
$var wire 1 ) empty $end
$var reg 5 , w_bin [4:0] $end
$var reg 5 - r_bin [4:0] $end
$var wire 5 . w_bin_next [4:0] $end
$var wire 5 / r_bin_next [4:0] $end
$var reg 5 0 w_gray [4:0] $end
$var reg 5 1 r_gray [4:0] $end
$var wire 5 2 w_gray_next [4:0] $end
$var wire 5 3 r_gray_next [4:0] $end
$var reg 5 4 w2r_meta [4:0] $end
$var reg 5 5 r2w_meta [4:0] $end
$var reg 5 6 w2r_safe [4:0] $end
$var reg 5 7 r2w_safe [4:0] $end

$scope module ram_inst $end
$var wire 1 % r_clk $end
$var wire 1 " w_clk $end
$var wire 1 8 wen $end
$var wire 4 9 waddr [3:0] $end
$var wire 8 $ wdata [7:0] $end
$var wire 1 : ren $end
$var wire 4 ; raddr [3:0] $end
$var reg 8 ' rdata [7:0] $end
$upscope $end

$upscope $end

$upscope $end

$enddefinitions $end

#0
$dumpvars
x)
x(
0%
0&
1!
08
0:
0"
0#
bxxxxxxxx +
bxxxxxxxxxxxxxxxxxxxxxxxxxxxxxxxx *
bxxxxx 5
bxxxxx 7
bxxxxx -
bxxxxx /
bxxxxx 1
bxxxxx 3
bxxxxxxxx '
bxxxx 9
bxxxx ;
bxxxxx 4
bxxxxx 6
bxxxxx ,
bxxxxx .
bxxxxx 0
bxxxxx 2
b00000000 $
$end
#5
1"
b00000 ,
b0000 9
b00000 0
b00000 5
b00000 7
b00000 .
b0xxxx 2
b00000 2
0(
#8
1%
b00000 -
b0000 ;
b00000 1
b00000 4
b00000 6
1)
b00000 /
b0xxxx 3
b00000 3
#10
0"
#15
1"
#16
0%
#20
0"
#24
1%
#25
1"
#30
0"
#32
0%
#35
1"
#40
1%
0"
#45
1"
#48
0%
#50
0!
0"
#55
1"
#56
1%
#60
0"
#64
0%
#65
1"
#70
0"
#72
1%
#75
1"
#80
0%
0"
#85
1"
#88
1%
#90
0"
#95
1"
#96
0%
#100
b00000000000000000000000000000000 *
0"
1#
18
b00001 .
b00001 2
#104
1%
#105
1"
b00001 ,
b0001 9
b00001 0
b00010 .
b00010 2
b00011 2
#110
0"
0#
08
b00000000000000000000000000000001 *
b00001 .
b00000 2
b00001 2
#112
0%
#115
1"
#120
1%
0"
1#
18
b00000001 $
b00010 .
b00010 2
b00011 2
b00001 4
#125
1"
b00010 ,
b0010 9
b00011 0
b00011 .
b00010 2
#128
0%
#130
0"
0#
08
b00000000 $
b00000000000000000000000000000010 *
b00010 .
b00011 2
#135
1"
#136
1%
b00011 4
b00001 6
0)
#140
0"
1#
18
b00000010 $
b00011 .
b00010 2
#144
0%
#145
1"
b00011 ,
b0011 9
b00010 0
b00100 .
b00101 2
b00110 2
#150
0"
0#
08
b00000000 $
b00000000000000000000000000000011 *
b00011 .
b00001 2
b00010 2
#152
1%
b00010 4
b00011 6
#155
1"
#160
0%
0"
1#
18
b00000011 $
b00100 .
b00101 2
b00110 2
#165
1"
b00100 ,
b0100 9
b00110 0
b00101 .
b00111 2
#168
1%
b00110 4
b00010 6
#170
0"
0#
08
b00000000 $
b00000000000000000000000000000100 *
b00100 .
b00110 2
#175
1"
#176
0%
#180
0"
1#
18
b00000100 $
b00101 .
b00111 2
#184
1%
b00110 6
#185
1"
b00101 ,
b0101 9
b00111 0
b00110 .
b00100 2
b00101 2
#190
0"
0#
08
b00000000 $
b00000000000000000000000000000101 *
b00101 .
b00110 2
b00111 2
#192
0%
#195
1"
#200
1%
0"
1#
18
b00000101 $
b00110 .
b00100 2
b00101 2
b00111 4
#205
1"
b00110 ,
b0110 9
b00101 0
b00111 .
b00100 2
#208
0%
#210
0"
0#
08
b00000000 $
b00000000000000000000000000000110 *
b00110 .
b00101 2
#215
1"
#216
1%
b00101 4
b00111 6
#220
0"
1#
18
b00000110 $
b00111 .
b00100 2
#224
0%
#225
1"
b00111 ,
b0111 9
b00100 0
b01000 .
b01011 2
b01100 2
#230
0"
0#
08
b00000000 $
b00000000000000000000000000000111 *
b00111 .
b00011 2
b00100 2
#232
1%
b00100 4
b00101 6
#235
1"
#240
0%
0"
1#
18
b00000111 $
b01000 .
b01011 2
b01100 2
#245
1"
b01000 ,
b1000 9
b01100 0
b01001 .
b01101 2
#248
1%
b01100 4
b00100 6
#250
0"
0#
08
b00000000 $
b00000000000000000000000000001000 *
b01000 .
b01100 2
#255
1"
#256
0%
#260
0"
1#
18
b00001000 $
b01001 .
b01101 2
#264
1%
b01100 6
#265
1"
b01001 ,
b1001 9
b01101 0
b01010 .
b01110 2
b01111 2
#270
0"
0#
08
b00000000 $
b00000000000000000000000000001001 *
b01001 .
b01100 2
b01101 2
#272
0%
#275
1"
#280
1%
0"
1#
18
b00001001 $
b01010 .
b01110 2
b01111 2
b01101 4
#285
1"
b01010 ,
b1010 9
b01111 0
b01011 .
b01110 2
#288
0%
#290
0"
0#
08
b00000000 $
b00000000000000000000000000001010 *
b01010 .
b01111 2
#295
1"
#296
1%
b01111 4
b01101 6
#300
0"
1#
18
b00001010 $
b01011 .
b01110 2
#304
0%
#305
1"
b01011 ,
b1011 9
b01110 0
b01100 .
b01001 2
b01010 2
#310
0"
0#
08
b00000000 $
b00000000000000000000000000001011 *
b01011 .
b01101 2
b01110 2
#312
1%
b01110 4
b01111 6
#315
1"
#320
0%
0"
1#
18
b00001011 $
b01100 .
b01001 2
b01010 2
#325
1"
b01100 ,
b1100 9
b01010 0
b01101 .
b01011 2
#328
1%
b01010 4
b01110 6
#330
0"
0#
08
b00000000 $
b00000000000000000000000000001100 *
b01100 .
b01010 2
#335
1"
#336
0%
#340
0"
1#
18
b00001100 $
b01101 .
b01011 2
#344
1%
b01010 6
#345
1"
b01101 ,
b1101 9
b01011 0
b01110 .
b01000 2
b01001 2
#350
0"
0#
08
b00000000 $
b00000000000000000000000000001101 *
b01101 .
b01010 2
b01011 2
#352
0%
#355
1"
#360
1%
0"
1#
18
b00001101 $
b01110 .
b01000 2
b01001 2
b01011 4
#365
1"
b01110 ,
b1110 9
b01001 0
b01111 .
b01000 2
#368
0%
#370
0"
0#
08
b00000000 $
b00000000000000000000000000001110 *
b01110 .
b01001 2
#375
1"
#376
1%
b01001 4
b01011 6
#380
0"
1#
18
b00001110 $
b01111 .
b01000 2
#384
0%
#385
1"
b01111 ,
b1111 9
b01000 0
b10000 .
b10111 2
b11000 2
#390
0"
0#
08
b00000000 $
b00000000000000000000000000001111 *
b01111 .
b00111 2
b01000 2
#392
1%
b01000 4
b01001 6
#395
1"
#400
0%
0"
1#
18
b00001111 $
b10000 .
b10111 2
b11000 2
#405
1"
b10000 ,
b0000 9
b11000 0
b10001 .
b11001 2
1(
08
b10000 .
b11000 2
#408
1%
b11000 4
b01000 6
#410
0"
0#
b00000000 $
b00000000000000000000000000010000 *
#415
1"
#416
0%
#420
0"
#424
1%
b11000 6
